Metadata-Version: 2.1
Name: fastapidi
Version: 0.1.3
Summary: Real dependency injection in fastapi
Home-page: https://github.com/Bloodielie/fastapidi
Author: Bloodie_lie
Author-email: riopro2812@gmail.com
License: MIT License
Platform: UNKNOWN
Classifier: Environment :: Web Environment
Classifier: Topic :: Internet
Classifier: Programming Language :: Python :: 3
Classifier: Programming Language :: Python :: 3.7
Classifier: Programming Language :: Python :: 3.8
Classifier: Programming Language :: Python :: 3.9
Requires-Python: >=3.7
